TOPSIS_Calc_102003257/102003257.py
TOPSIS_Calc_102003257/__init__.py
Topsis_Karanjot_102003257-1.0.1.dist-info/LICENSE
Topsis_Karanjot_102003257-1.0.1.dist-info/METADATA
Topsis_Karanjot_102003257-1.0.1.dist-info/WHEEL
Topsis_Karanjot_102003257-1.0.1.dist-info/entry_points.txt
Topsis_Karanjot_102003257-1.0.1.dist-info/top_level.txt
Topsis_Karanjot_102003257-1.0.1.dist-info/RECORD
