Metadata-Version: 2.1
Name: Topsis-Karanjot-102003257
Version: 1.0.1
Summary: A package -> Calculates Topsis Score and Rank them accordingly
Author: Karanjot Singh
Author-email: ksingh5_be20@thapar.edu
License: MIT
Classifier: Programming Language :: Python :: 3
Classifier: License :: OSI Approved :: MIT License
Classifier: Operating System :: OS Independent
License-File: LICENSE
Requires-Dist: pandas
